aqualogicwireless/__init__.py
aqualogicwireless/cli.py
aqualogicwireless/core.py
aqualogicwireless/keys.py
aqualogicwireless/states.py
aqualogicwireless/web.py
aqualogicwireless-1.0.9.dist-info/LICENSE.txt
aqualogicwireless-1.0.9.dist-info/METADATA
aqualogicwireless-1.0.9.dist-info/WHEEL
aqualogicwireless-1.0.9.dist-info/top_level.txt
aqualogicwireless-1.0.9.dist-info/RECORD
