Metadata-Version: 2.1
Name: aqualogicwireless
Version: 1.0.9
Summary: Library for interfacing with a Hayward/Goldline AquaLogic/ProLogic pool controller.
Home-page: https://github.com/swiftlee/aqualogic
Author: Sean Wilson / Jonathan Conlin
Author-email: horizonman34@gmail.com
License: MIT
Platform: UNKNOWN
Classifier: Development Status :: 5 - Production/Stable
Classifier: Intended Audience :: Developers
Classifier: Topic :: Software Development :: Embedded Systems
Classifier: License :: OSI Approved :: MIT License
Classifier: Programming Language :: Python :: 3
Classifier: Programming Language :: Python :: 3.2
Classifier: Programming Language :: Python :: 3.3
Classifier: Programming Language :: Python :: 3.4
License-File: LICENSE.txt
Requires-Dist: pyserial
Requires-Dist: aiohttp
